setup.py
sid_probability/Binomialdistribution.py
sid_probability/Gaussiandistribution.py
sid_probability/Generaldistribution.py
sid_probability/__init__.py
sid_probability.egg-info/PKG-INFO
sid_probability.egg-info/SOURCES.txt
sid_probability.egg-info/dependency_links.txt
sid_probability.egg-info/not-zip-safe
sid_probability.egg-info/top_level.txt