Metadata-Version: 1.0
Name: sid-probability
Version: 0.1
Summary: Gaussian distributions
Home-page: UNKNOWN
Author: Siddhartha Shrestha
Author-email: shrestha.siddhartha06@outlook.com
License: UNKNOWN
Platform: UNKNOWN
